{
  "posts": [
    {
      "id": 4,
      "title": "ăn j k6"
    }
  ],
  "comments": [
    {
      "id": 1,
      "title": "hehe",
      "postId": "3"
    },
    {
      "id": 2,
      "title": "hehe",
      "postId": "3"
    },
    {
      "id": 4,
      "title": "hihi",
      "postId": "3"
    },
    {
      "id": 8
    },
    {
      "id": 9,
      "name": "Toán",
      "comment": "nay ăn cái j đây lẩu thôi",
      "postId": "1"
    }
  ],
  " posts": [
    {
      "title": "mariaaa",
      "id": 1
    },
    {
      "title": "ăn j k2",
      "id": 2
    }
  ]
}